LICENSE
MANIFEST.in
README.md
setup.py
pytest_send_email/__init__.py
pytest_send_email/plugin.py
pytest_send_email.egg-info/PKG-INFO
pytest_send_email.egg-info/SOURCES.txt
pytest_send_email.egg-info/dependency_links.txt
pytest_send_email.egg-info/entry_points.txt
pytest_send_email.egg-info/requires.txt
pytest_send_email.egg-info/top_level.txt
pytest_send_email.egg-info/zip-safe
tests/test_pytest_send_email.py