Metadata-Version: 2.1
Name: pytest-send-email
Version: 0.1.1
Summary: Send pytest execution result email
Home-page: https://github.com/hanzhichao/pytest-send-email
Author: Han Zhichao
Author-email: superhin@126.com
License: MIT license
Keywords: pytest,py.test,email,smtp
Classifier: Framework :: Pytest
Classifier: Programming Language :: Python
Classifier: Topic :: Software Development :: Testing
Classifier: Programming Language :: Python :: 3.7
License-File: LICENSE
Requires-Dist: pytest
Requires-Dist: pytest-runner
